medcat_den/__init__.py
medcat_den/__main__.py
medcat_den/backend.py
medcat_den/base.py
medcat_den/config.py
medcat_den/den.py
medcat_den/py.typed
medcat_den/utils.py
medcat_den/wrappers.py
medcat_den/addons/__init__.py
medcat_den/addons/addons.py
medcat_den/backend_impl/__init__.py
medcat_den/backend_impl/file_den.py
medcat_den/cache/__init__.py
medcat_den/cache/local_cache.py
medcat_den/injection/__init__.py
medcat_den/injection/medcat_injector.py
medcat_den/injection/run_injected.py
medcat_den/resolver/__init__.py
medcat_den/resolver/resolver.py
medcat_den-0.5.2.dist-info/licenses/LICENSE
medcat_den-0.5.2.dist-info/METADATA
medcat_den-0.5.2.dist-info/WHEEL
medcat_den-0.5.2.dist-info/top_level.txt
medcat_den-0.5.2.dist-info/RECORD
