Metadata-Version: 2.4
Name: medcat_den
Version: 0.5.2
Summary: Model storage and lifecycle management for MedCAT with support for local, remote [TODO], and cloud [TODO] backends.
Author-email: Mart Ratas <mart.ratas@kcl.ac.uk>
License: Apache-2.0
Project-URL: Homepage, https://github.com/CogStack/cogstack-nlp/tree/main/medcat-den
Project-URL: Repository, https://github.com/CogStack/cogstack-nlp/tree/main/medcat-den
Project-URL: Issues, https://github.com/CogStack/cogstack-nlp/issues
Keywords: NLP,medical,MedCAT,model-registry
Classifier: Development Status :: 3 - Alpha
Classifier: Intended Audience :: Science/Research
Classifier: Topic :: Scientific/Engineering :: Artificial Intelligence
Classifier: Programming Language :: Python :: 3
Classifier: Programming Language :: Python :: 3.10
Classifier: Programming Language :: Python :: 3.11
Classifier: Programming Language :: Python :: 3.12
Classifier: License :: OSI Approved :: Apache Software License
Requires-Python: >=3.10
License-File: LICENSE
Requires-Dist: medcat[deid,meta-cat,rel-cat,spacy]>=2.0.0
Requires-Dist: pydantic<3,>=2
Requires-Dist: platformdirs<5.0,>=4.4.0
Requires-Dist: diskcache<6.0,>=5.6.3
Provides-Extra: dev
Requires-Dist: pytest; extra == "dev"
Requires-Dist: ruff; extra == "dev"
Requires-Dist: mypy; extra == "dev"
Requires-Dist: diskcache-stubs; extra == "dev"
Dynamic: license-file
